{
  "db_name": "PostgreSQL",
  "query": "INSERT INTO research_templates\n             (id, label, description, skeleton, writing_instructions, outline_mode, scope, created_by)\n           VALUES ($1, $2, $3, $4, $5, $6, $7, $8)",
  "describe": {
    "columns": [],
    "parameters": {
      "Left": [
        "Uuid",
        "Text",
        "Text",
        "Jsonb",
        "Text",
        "Text",
        "Text",
        "Uuid"
      ]
    },
    "nullable": []
  },
  "hash": "126ba7ec2610c72f29e10bcad896c021cb735c749333cbcc7477294414d6812f"
}
